[
    {
        "id":  "ir-2017-I-q93",
        "subject":  "International Relations",
        "topic":  "Bilateral, Summits \u0026 Diplomacy",
        "subtopic":  "",
        "topicOriginal":  "Bilateral, Summits \u0026 Diplomacy",
        "year":  2017,
        "session":  "I",
        "paper":  "CDS 2017-I",
        "qno":  93,
        "ref":  "CDS 2017-I, Q.93",
        "stem":  "Which country signed a Memorandum of Understanding with India for promoting the production of pigeon pea and other pulses in July 2016?",
        "subs":  [

                 ],
        "options":  [
                        "South Africa",
                        "Syria",
                        "Egypt",
                        "Mozambique"
                    ],
        "answer":  "d",
        "explanation":  "To secure long-term pulse supplies, India signed an MoU with Mozambique in 2016 to boost the production of pigeon pea (tur/arhar) and other pulses there for export to India — part of India\u0027s strategy to address its chronic pulse shortfall and price volatility. (A current-affairs item.)",
        "defective":  false
    },
    {
        "id":  "ir-2018-II-q64",
        "subject":  "International Relations",
        "topic":  "Bilateral, Summits \u0026 Diplomacy",
        "subtopic":  "",
        "topicOriginal":  "Bilateral, Summits \u0026 Diplomacy",
        "year":  2018,
        "session":  "II",
        "paper":  "CDS 2018-II",
        "qno":  64,
        "ref":  "CDS 2018-II, Q.64",
        "stem":  "The 2+2 Bilateral Dialogue held in September 2018 was between",
        "subs":  [

                 ],
        "options":  [
                        "External Affairs and Defence Ministers of India with their US counterparts",
                        "Finance and Defence Ministers of India with Russia",
                        "Home and Defence Ministers of India and Pakistan",
                        "External Affairs and Defence Ministers of India with Pakistan"
                    ],
        "answer":  "a",
        "explanation":  "A \"2+2\" dialogue pairs the foreign and defence ministers of two countries to coordinate strategic and security matters. The inaugural India-US 2+2 dialogue (September 2018) brought together India\u0027s External Affairs and Defence Ministers with the US Secretaries of State and Defense, and produced the COMCASA defence-communications agreement. (A current-affairs item.)",
        "defective":  false
    },
    {
        "id":  "ir-2025-II-q1",
        "subject":  "International Relations",
        "topic":  "Regional Organizations",
        "subtopic":  "",
        "topicOriginal":  "Regional Organizations",
        "year":  2025,
        "session":  "II",
        "paper":  "CDS 2025-II",
        "qno":  1,
        "ref":  "CDS 2025-II, Q.1",
        "stem":  "Consider the following international events and arrange them in chronological order:",
        "subs":  [
                     "1. Signing of the Simla Agreement",
                     "2. Agra Summit between India and Pakistan",
                     "3. Signing of the SAARC Charter at the First SAARC Summit",
                     "4. India\u0027s first nuclear test"
                 ],
        "options":  [
                        "1, 2, 3, 4",
                        "3, 1, 4, 2",
                        "1, 4, 3, 2",
                        "4, 3, 1, 2"
                    ],
        "answer":  "c",
        "explanation":  "Chronological order: Simla Agreement (1972, 1), India\u0027s first nuclear test (1974, 4), SAARC Charter at the First SAARC Summit (1985, 3), Agra Summit (2001, 2). Hence 1, 4, 3, 2 (option c). (The source had split this single ordering question into fragments and omitted the nuclear-test event; reconstructed here.)",
        "defective":  false
    },
    {
        "id":  "ir-2017-I-q92",
        "subject":  "International Relations",
        "topic":  "Multilateral Groupings",
        "subtopic":  "",
        "topicOriginal":  "Multilateral Groupings",
        "year":  2017,
        "session":  "I",
        "paper":  "CDS 2017-I",
        "qno":  92,
        "ref":  "CDS 2017-I, Q.92",
        "stem":  "The BRICS Summit, 2016 was held in",
        "subs":  [

                 ],
        "options":  [
                        "Brazil",
                        "China",
                        "India",
                        "South Africa"
                    ],
        "answer":  "c",
        "explanation":  "The 8th BRICS Summit (2016) was hosted by India at Goa. (BRICS = Brazil, Russia, India, China, South Africa.) (A current-affairs item.)",
        "defective":  false
    },
    {
        "id":  "ir-2018-I-q113",
        "subject":  "International Relations",
        "topic":  "Multilateral Groupings",
        "subtopic":  "",
        "topicOriginal":  "Multilateral Groupings",
        "year":  2018,
        "session":  "I",
        "paper":  "CDS 2018-I",
        "qno":  113,
        "ref":  "CDS 2018-I, Q.113",
        "stem":  "The first BRICS Summit after the inclusion of South Africa was held at",
        "subs":  [

                 ],
        "options":  [
                        "Brasilia",
                        "Sanya",
                        "Yekaterinburg",
                        "Durban"
                    ],
        "answer":  "b",
        "explanation":  "South Africa joined the grouping (turning \"BRIC\" into \"BRICS\") in 2010, and the first summit with South Africa as a member was the 2011 summit at Sanya, China. (The first-ever BRIC summit, in 2009, was at Yekaterinburg, Russia.) (A current-affairs item.)",
        "defective":  false
    },
    {
        "id":  "ir-2019-I-q120",
        "subject":  "International Relations",
        "topic":  "Multilateral Groupings",
        "subtopic":  "",
        "topicOriginal":  "Multilateral Groupings",
        "year":  2019,
        "session":  "I",
        "paper":  "CDS 2019-I",
        "qno":  120,
        "ref":  "CDS 2019-I, Q.120",
        "stem":  "The 11th BRICS Summit in 2019 was hosted by",
        "subs":  [

                 ],
        "options":  [
                        "China",
                        "Russia",
                        "Brazil",
                        "India"
                    ],
        "answer":  "c",
        "explanation":  "The 11th BRICS Summit (2019) was hosted by Brazil (Brasilia). (A current-affairs item.)",
        "defective":  false
    },
    {
        "id":  "ir-2020-I-q119",
        "subject":  "International Relations",
        "topic":  "Multilateral Groupings",
        "subtopic":  "",
        "topicOriginal":  "Multilateral Groupings",
        "year":  2020,
        "session":  "I",
        "paper":  "CDS 2020-I",
        "qno":  119,
        "ref":  "CDS 2020-I, Q.119",
        "stem":  "The BRICS Summit, 2020 was hosted by",
        "subs":  [

                 ],
        "options":  [
                        "India",
                        "China",
                        "Russia",
                        "Brazil"
                    ],
        "answer":  "c",
        "explanation":  "The 12th BRICS Summit (2020) was hosted by Russia (held virtually due to COVID-19). (A current-affairs item.)",
        "defective":  false
    },
    {
        "id":  "ir-2021-I-q82",
        "subject":  "International Relations",
        "topic":  "Multilateral Groupings",
        "subtopic":  "",
        "topicOriginal":  "Multilateral Groupings",
        "year":  2021,
        "session":  "I",
        "paper":  "CDS 2021-I",
        "qno":  82,
        "ref":  "CDS 2021-I, Q.82",
        "stem":  "Which is not a member of the Quad group of nations?",
        "subs":  [

                 ],
        "options":  [
                        "France",
                        "USA",
                        "Australia",
                        "Japan"
                    ],
        "answer":  "a",
        "explanation":  "The Quad (Quadrilateral Security Dialogue) comprises India, the USA, Japan and Australia — four democracies cooperating on a free and open Indo-Pacific. France is not a member (a). (A current-affairs item.)",
        "defective":  false
    },
    {
        "id":  "ir-2022-I-q48",
        "subject":  "International Relations",
        "topic":  "Multilateral Groupings",
        "subtopic":  "",
        "topicOriginal":  "Multilateral Groupings",
        "year":  2022,
        "session":  "I",
        "paper":  "CDS 2022-I",
        "qno":  48,
        "ref":  "CDS 2022-I, Q.48",
        "stem":  "Which best describes BRICS?",
        "subs":  [

                 ],
        "options":  [
                        "A group of five nuclear powers",
                        "A group of five industrialized nations",
                        "A group of five major emerging economies",
                        "A group of five potential UNSC members from the Global South"
                    ],
        "answer":  "c",
        "explanation":  "BRICS is best understood as a grouping of five major emerging (developing) economies — Brazil, Russia, India, China and South Africa — that cooperate on economic and geopolitical issues and seek a greater voice for the developing world. They are not all nuclear powers or industrialized nations.",
        "defective":  false
    },
    {
        "id":  "ir-2023-I-q111",
        "subject":  "International Relations",
        "topic":  "Multilateral Groupings",
        "subtopic":  "",
        "topicOriginal":  "Multilateral Groupings",
        "year":  2023,
        "session":  "I",
        "paper":  "CDS 2023-I",
        "qno":  111,
        "ref":  "CDS 2023-I, Q.111",
        "stem":  "Who was not in the core leadership of the Non-Aligned Movement (NAM) in its formative phase?",
        "subs":  [

                 ],
        "options":  [
                        "Kwame Nkrumah",
                        "Gamal Abdel Nasser",
                        "Jawaharlal Nehru",
                        "Fidel Castro"
                    ],
        "answer":  "d",
        "explanation":  "NAM\u0027s founding leaders were Jawaharlal Nehru (India), Gamal Abdel Nasser (Egypt), Josip Broz Tito (Yugoslavia), Sukarno (Indonesia) and Kwame Nkrumah (Ghana). Fidel Castro (Cuba) rose to prominence in NAM later (he hosted the 1979 summit), but was not part of the formative-phase core leadership. Hence d.",
        "defective":  false
    },
    {
        "id":  "ir-2024-II-q41",
        "subject":  "International Relations",
        "topic":  "Multilateral Groupings",
        "subtopic":  "",
        "topicOriginal":  "Multilateral Groupings",
        "year":  2024,
        "session":  "II",
        "paper":  "CDS 2024-II",
        "qno":  41,
        "ref":  "CDS 2024-II, Q.41",
        "stem":  "About the Shanghai Cooperation Organization (SCO):",
        "subs":  [
                     "1. The official languages are Russian and Chinese.",
                     "2. The SCO enjoys observer status in the UN General Assembly.",
                     "3. The SCO consists of 13 member states."
                 ],
        "options":  [
                        "1 only",
                        "1 and 3",
                        "1 and 2",
                        "2 and 3"
                    ],
        "answer":  "c",
        "explanation":  "The SCO\u0027s official working languages are Russian and Chinese (1), and it holds observer status at the UN General Assembly (2). Statement 3 is wrong — the SCO does not have 13 member states (after Iran joined in 2023 and Belarus in 2024 it has around 9-10 full members). Hence 1 and 2.",
        "defective":  false
    },
    {
        "id":  "ir-2017-I-q56",
        "subject":  "International Relations",
        "topic":  "Regional Organizations",
        "subtopic":  "",
        "topicOriginal":  "Regional Organizations",
        "year":  2017,
        "session":  "I",
        "paper":  "CDS 2017-I",
        "qno":  56,
        "ref":  "CDS 2017-I, Q.56",
        "stem":  "Which statement is not correct about the SAARC?",
        "subs":  [

                 ],
        "options":  [
                        "Its headquarters is in Kathmandu.",
                        "China is the only country with Observer status in SAARC.",
                        "The first SAARC Summit was held in Dhaka.",
                        "The eighteenth SAARC Summit was held in Nepal."
                    ],
        "answer":  "b",
        "explanation":  "SAARC (founded 1985, secretariat at Kathmandu) has multiple observers — China, the USA, the EU, Japan, Iran, South Korea, etc. — so \"China is the only Observer\" is false. The first summit was at Dhaka (1985) and the 18th at Kathmandu, Nepal (2014). Hence b is the incorrect statement.",
        "defective":  false
    },
    {
        "id":  "ir-2019-II-q12",
        "subject":  "International Relations",
        "topic":  "UN \u0026 International Agencies",
        "subtopic":  "",
        "topicOriginal":  "UN \u0026 International Agencies",
        "year":  2019,
        "session":  "II",
        "paper":  "CDS 2019-II",
        "qno":  12,
        "ref":  "CDS 2019-II, Q.12",
        "stem":  "Which statement about the Organization of Islamic Cooperation (OIC) is not correct?",
        "subs":  [

                 ],
        "options":  [
                        "Its permanent Secretariat is at Jeddah.",
                        "It works to safeguard the interests of the Muslim world and promote international peace.",
                        "It is the largest inter-governmental organization in the world.",
                        "It has consultative and cooperative relations with the UN."
                    ],
        "answer":  "c",
        "explanation":  "The OIC (57 member states, secretariat at Jeddah) is the second-largest inter-governmental organisation after the United Nations — so calling it \"the largest\" (c) is false. The other statements are correct.",
        "defective":  false
    },
    {
        "id":  "ir-2019-I-q18",
        "subject":  "International Relations",
        "topic":  "UN \u0026 International Agencies",
        "subtopic":  "",
        "topicOriginal":  "UN \u0026 International Agencies",
        "year":  2019,
        "session":  "I",
        "paper":  "CDS 2019-I",
        "qno":  18,
        "ref":  "CDS 2019-I, Q.18",
        "stem":  "The UN observes the International Day of Rural Women on",
        "subs":  [

                 ],
        "options":  [
                        "15th July",
                        "15th August",
                        "15th September",
                        "15th October"
                    ],
        "answer":  "d",
        "explanation":  "The International Day of Rural Women is observed on 15 October, recognising rural women\u0027s role in agriculture and rural development. (A days/observances item.)",
        "defective":  false
    },
    {
        "id":  "ir-2020-I-q83",
        "subject":  "International Relations",
        "topic":  "UN \u0026 International Agencies",
        "subtopic":  "",
        "topicOriginal":  "UN \u0026 International Agencies",
        "year":  2020,
        "session":  "I",
        "paper":  "CDS 2020-I",
        "qno":  83,
        "ref":  "CDS 2020-I, Q.83",
        "stem":  "The Global Goalkeeper Award is given by",
        "subs":  [

                 ],
        "options":  [
                        "the Bill and Melinda Gates Foundation",
                        "the UN Environment Programme",
                        "the Kellogg School of Management",
                        "the World Meteorological Organization"
                    ],
        "answer":  "a",
        "explanation":  "The Global Goalkeeper Award is presented by the Bill \u0026 Melinda Gates Foundation to recognise progress toward the Sustainable Development Goals (PM Modi received it in 2019 for the Swachh Bharat Mission). (A current-affairs item.)",
        "defective":  false
    },
    {
        "id":  "ir-2021-I-q40",
        "subject":  "International Relations",
        "topic":  "UN \u0026 International Agencies",
        "subtopic":  "",
        "topicOriginal":  "UN \u0026 International Agencies",
        "year":  2021,
        "session":  "I",
        "paper":  "CDS 2021-I",
        "qno":  40,
        "ref":  "CDS 2021-I, Q.40",
        "stem":  "Which approach to human development, initially proposed by the ILO, emphasised health, education, food, water supply, sanitation and housing?",
        "subs":  [

                 ],
        "options":  [
                        "Welfare approach",
                        "Basic needs approach",
                        "Income approach",
                        "Capability approach"
                    ],
        "answer":  "b",
        "explanation":  "The Basic Needs Approach, promoted by the ILO in the 1970s, defined development in terms of meeting people\u0027s minimum basic needs — food, water, sanitation, housing, health and education — rather than just raising income. (The capability approach is Amartya Sen\u0027s.) (An economics/development item.)",
        "defective":  false
    },
    {
        "id":  "ir-2021-II-q114",
        "subject":  "International Relations",
        "topic":  "UN \u0026 International Agencies",
        "subtopic":  "",
        "topicOriginal":  "UN \u0026 International Agencies",
        "year":  2021,
        "session":  "II",
        "paper":  "CDS 2021-II",
        "qno":  114,
        "ref":  "CDS 2021-II, Q.114",
        "stem":  "Which country was recently awarded a certification by the WHO?",
        "subs":  [

                 ],
        "options":  [
                        "Pakistan",
                        "Bhutan",
                        "China",
                        "Nepal"
                    ],
        "answer":  "c",
        "explanation":  "In 2021 the WHO certified China as malaria-free after it reported zero indigenous cases for four consecutive years — a major public-health milestone. (A current-affairs item; worth confirming the intended certification against the official key.)",
        "defective":  false
    },
    {
        "id":  "ir-2022-II-q113",
        "subject":  "International Relations",
        "topic":  "Bilateral, Summits \u0026 Diplomacy",
        "subtopic":  "",
        "topicOriginal":  "Bilateral, Summits \u0026 Diplomacy",
        "year":  2022,
        "session":  "II",
        "paper":  "CDS 2022-II",
        "qno":  113,
        "ref":  "CDS 2022-II, Q.113",
        "stem":  "Who usurped power in Kanyakubja after the death of Harshavardhana?",
        "subs":  [

                 ],
        "options":  [
                        "Adityasena",
                        "Arunashva",
                        "Shashanka",
                        "Lalitaditya"
                    ],
        "answer":  "b",
        "explanation":  "After Harshavardhana died (647 CE) without an heir, his minister Arunashva (Arjuna) seized power at Kanauj (Kanyakubja) — and then attacked the Chinese envoy Wang Xuance, triggering a Tibetan-Nepalese intervention. (A history item.)",
        "defective":  false
    },
    {
        "id":  "ir-2023-I-q84",
        "subject":  "International Relations",
        "topic":  "UN \u0026 International Agencies",
        "subtopic":  "",
        "topicOriginal":  "UN \u0026 International Agencies",
        "year":  2023,
        "session":  "I",
        "paper":  "CDS 2023-I",
        "qno":  84,
        "ref":  "CDS 2023-I, Q.84",
        "stem":  "Who was honoured with the UN Environment Programme\u0027s 2022 \"Champions of the Earth\" award in the Entrepreneurial Vision category?",
        "subs":  [

                 ],
        "options":  [
                        "Ela Bhatt",
                        "Amit Dasgupta",
                        "Purnima Devi Barman",
                        "Vanshika Parmar"
                    ],
        "answer":  "c",
        "explanation":  "Wildlife biologist Purnima Devi Barman, who leads the \"Hargila Army\" of women to protect the endangered Greater Adjutant stork in Assam, won the UNEP Champions of the Earth award (2022) in the Entrepreneurial Vision category. (A current-affairs item.)",
        "defective":  false
    },
    {
        "id":  "ir-2023-II-q78",
        "subject":  "International Relations",
        "topic":  "UN \u0026 International Agencies",
        "subtopic":  "",
        "topicOriginal":  "UN \u0026 International Agencies",
        "year":  2023,
        "session":  "II",
        "paper":  "CDS 2023-II",
        "qno":  78,
        "ref":  "CDS 2023-II, Q.78",
        "stem":  "Which is not a permanent member of the UN Security Council?",
        "subs":  [

                 ],
        "options":  [
                        "France",
                        "China",
                        "Japan",
                        "United Kingdom"
                    ],
        "answer":  "c",
        "explanation":  "The five permanent members (P5) of the UN Security Council are the USA, Russia, China, France and the United Kingdom. Japan is not a permanent member (it has frequently served as a non-permanent member and seeks a permanent seat). Hence c.",
        "defective":  false
    },
    {
        "id":  "ir-2024-II-q36",
        "subject":  "International Relations",
        "topic":  "UN \u0026 International Agencies",
        "subtopic":  "",
        "topicOriginal":  "UN \u0026 International Agencies",
        "year":  2024,
        "session":  "II",
        "paper":  "CDS 2024-II",
        "qno":  36,
        "ref":  "CDS 2024-II, Q.36",
        "stem":  "Which UN organization has not been awarded the Nobel Prize?",
        "subs":  [

                 ],
        "options":  [
                        "WFP",
                        "ILO",
                        "UNESCO",
                        "UNHCR"
                    ],
        "answer":  "c",
        "explanation":  "The World Food Programme (WFP, 2020), the International Labour Organization (ILO, 1969) and the UN High Commissioner for Refugees (UNHCR, 1954 and 1981) have all won the Nobel Peace Prize. UNESCO has not been awarded the Nobel Peace Prize. Hence c.",
        "defective":  false
    },
    {
        "id":  "ir-2024-II-q43",
        "subject":  "International Relations",
        "topic":  "UN \u0026 International Agencies",
        "subtopic":  "",
        "topicOriginal":  "UN \u0026 International Agencies",
        "year":  2024,
        "session":  "II",
        "paper":  "CDS 2024-II",
        "qno":  43,
        "ref":  "CDS 2024-II, Q.43",
        "stem":  "For which matters before the UN General Assembly is a two-thirds majority of members present and voting required?",
        "subs":  [
                     "1. Admission of new members to the UN",
                     "2. Election of the non-permanent members of the Security Council",
                     "3. Election of members of the Economic and Social Council."
                 ],
        "options":  [
                        "1 and 2 only",
                        "2 and 3 only",
                        "1 and 3 only",
                        "1, 2 and 3"
                    ],
        "answer":  "d",
        "explanation":  "Under Article 18 of the UN Charter, decisions on \"important questions\" require a two-thirds majority — these include the admission of new members (1), election of non-permanent UNSC members (2) and election of ECOSOC members (3). Hence all three.",
        "defective":  false
    },
    {
        "id":  "ir-2025-I-q82",
        "subject":  "International Relations",
        "topic":  "UN \u0026 International Agencies",
        "subtopic":  "",
        "topicOriginal":  "UN \u0026 International Agencies",
        "year":  2025,
        "session":  "I",
        "paper":  "CDS 2025-I",
        "qno":  82,
        "ref":  "CDS 2025-I, Q.82",
        "stem":  "Which UN agency has received the Nobel Prize more than once?",
        "subs":  [

                 ],
        "options":  [
                        "ILO",
                        "WFP",
                        "UNICEF",
                        "UNHCR"
                    ],
        "answer":  "d",
        "explanation":  "The UN High Commissioner for Refugees (UNHCR) has won the Nobel Peace Prize twice — in 1954 and 1981 — for its work protecting refugees. (ILO, WFP and UNICEF have each won once.) Hence d.",
        "defective":  false
    },
    {
        "id":  "ir-2025-I-q84",
        "subject":  "International Relations",
        "topic":  "UN \u0026 International Agencies",
        "subtopic":  "",
        "topicOriginal":  "UN \u0026 International Agencies",
        "year":  2025,
        "session":  "I",
        "paper":  "CDS 2025-I",
        "qno":  84,
        "ref":  "CDS 2025-I, Q.84",
        "stem":  "The International Day of Democracy, decided by a UN General Assembly resolution, is observed on",
        "subs":  [

                 ],
        "options":  [
                        "20 January",
                        "1 July",
                        "15 September",
                        "9 December"
                    ],
        "answer":  "c",
        "explanation":  "The UN observes the International Day of Democracy on 15 September each year, to review the state of democracy worldwide. (A days/observances item.)",
        "defective":  false
    }
]